{"cameraMode":{"drawMode":0,"name":"Shaded","section":"Shading Mode"},"sceneLighting":false,"audioPlay":false,"sceneViewState":{"m_AlwaysRefresh":false,"showFog":true,"showSkybox":false,"showFlares":true,"showImageEffects":true,"showParticleSystems":true,"showVisualEffectGraphs":true,"m_FxEnabled":true},"in2DMode":false,"pivot":{"x":385.0,"y":216.5,"z":0.0},"rotation":{"x":0.023378001525998117,"y":-0.9570645093917847,"z":0.08250553905963898,"w":0.2789084315299988},"size":441.6981506347656,"orthographic":false}